element/__init__.py
element/api.py
element/exceptions.py
element/solidfire_element_api.py
element/utils.py
element/cli/__init__.py
element/cli/cli.py
element/cli/formatter.py
element/cli/parser.py
element/cli/utils.py
element/cli/commands/__init__.py
element/cli/commands/cmd_account.py
element/cli/commands/cmd_async.py
element/cli/commands/cmd_backuptarget.py
element/cli/commands/cmd_cluster.py
element/cli/commands/cmd_clusteradmin.py
element/cli/commands/cmd_connection.py
element/cli/commands/cmd_drive.py
element/cli/commands/cmd_hardware.py
element/cli/commands/cmd_idp.py
element/cli/commands/cmd_initiators.py
element/cli/commands/cmd_ldap.py
element/cli/commands/cmd_lldp.py
element/cli/commands/cmd_logging.py
element/cli/commands/cmd_network.py
element/cli/commands/cmd_node.py
element/cli/commands/cmd_pairing.py
element/cli/commands/cmd_restart.py
element/cli/commands/cmd_schedule.py
element/cli/commands/cmd_security.py
element/cli/commands/cmd_sensors.py
element/cli/commands/cmd_service.py
element/cli/commands/cmd_sfapi.py
element/cli/commands/cmd_snapmirror.py
element/cli/commands/cmd_snapshot.py
element/cli/commands/cmd_snmp.py
element/cli/commands/cmd_ssh.py
element/cli/commands/cmd_storagecontainer.py
element/cli/commands/cmd_test.py
element/cli/commands/cmd_virtualnetwork.py
element/cli/commands/cmd_virtualvolume.py
element/cli/commands/cmd_volume.py
element/cli/commands/cmd_volumeaccessgroup.py
element/managers/__init__.py
solidfire_cli-1.7.0.154.dist-info/DESCRIPTION.rst
solidfire_cli-1.7.0.154.dist-info/METADATA
solidfire_cli-1.7.0.154.dist-info/RECORD
solidfire_cli-1.7.0.154.dist-info/WHEEL
solidfire_cli-1.7.0.154.dist-info/entry_points.txt
solidfire_cli-1.7.0.154.dist-info/metadata.json
solidfire_cli-1.7.0.154.dist-info/top_level.txt
