Metadata-Version: 2.0
Name: solidfire-cli
Version: 1.7.0.154
Summary: A python client and CLI for accessing the SolidFire API.
Home-page: UNKNOWN
Author: UNKNOWN
Author-email: UNKNOWN
License: Apache License 2.0
Keywords: element
Platform: UNKNOWN
Classifier: Environment :: Console
Classifier: Environment :: Web Environment
Classifier: Intended Audience :: Developers
Classifier: Intended Audience :: System Administrators
Classifier: License :: OSI Approved :: Apache Software License
Classifier: Operating System :: OS Independent
Classifier: Topic :: Software Development :: Libraries :: Python Modules
Classifier: Programming Language :: Python :: 3
Classifier: Programming Language :: Python :: 3.4
Classifier: Programming Language :: Python :: 3.3
Classifier: Programming Language :: Python :: 2.7
Requires-Dist: FileLock
Requires-Dist: click (>=5)
Requires-Dist: future
Requires-Dist: getpass2
Requires-Dist: jsonpickle (>=0.9.3)
Requires-Dist: pycryptodome (>=2.6.1)
Requires-Dist: setuptools
Requires-Dist: simplejson
Requires-Dist: solidfire-sdk-python (>=1.2)
